bgisimtool/__init__.py
bgisimtool/fileUtils.py
bgisimtool/histogram.py
bgisimtool/ipmsim.py
bgisimtool/mathfunc.py
bgisimtool/plot_io.py
bgisimtool/process_results.py
bgisimtool/skeleton.py
BGISimtool-0.1.dist-info/LICENSE.txt
BGISimtool-0.1.dist-info/METADATA
BGISimtool-0.1.dist-info/WHEEL
BGISimtool-0.1.dist-info/entry_points.txt
BGISimtool-0.1.dist-info/top_level.txt
BGISimtool-0.1.dist-info/RECORD
