Metadata-Version: 2.1
Name: BGISimtool
Version: 0.1
Summary: A package to process or manage simulations for the CERN BGIs.
Home-page: https://gitlab.cern.ch/slevasse/bgisimtool
Author: Swann Levasseur
Author-email: swann.levasseur@cern.ch
License: MIT
Project-URL: Source, https://gitlab.cern.ch/slevasse/bgisimtool
Platform: any
Classifier: Development Status :: 1 - Planning
Classifier: Programming Language :: Python
License-File: LICENSE.txt
Requires-Dist: importlib-metadata
Requires-Dist: pandas
Requires-Dist: numpy
Requires-Dist: scipy
Requires-Dist: matplotlib
Provides-Extra: testing
Requires-Dist: setuptools ; extra == 'testing'
Requires-Dist: pytest ; extra == 'testing'
Requires-Dist: pytest-cov ; extra == 'testing'
